vulnersx.py
vulnersx-1.0.0.dist-info/WHEEL
vulnersx-1.0.0.dist-info/METADATA
vulnersx-1.0.0.dist-info/RECORD
