Metadata-Version: 2.1
Name: vulnersx
Version: 1.0.0
Summary: VulnersX : powerful tool for efficiently searching and analyzing software vulnerabilities.
Home-page: https://github.com/symbolexe/VulnersX
License: MIT
Author: Yasin Saffari
Author-email: symbolexe@proton.me
